ispositive/__init__.py
ispositive/check.py
ispositive-0.1.dist-info/licenses/LICENSE
ispositive-0.1.dist-info/METADATA
ispositive-0.1.dist-info/WHEEL
ispositive-0.1.dist-info/top_level.txt
ispositive-0.1.dist-info/RECORD
